{
  "title": "Shop",
  "menu.main": "Main",
  "basket.title": "Cart",
  "basket.open": "Open",
  "basket.close": "Close",
  "basket.inBasket": "In cart",
  "basket.empty": "empty",
  "basket.articles": {
    "one": "article",
    "other": "articles"
  },
  "basket.total": "Total",
  "basket.unit": "pcs",
  "basket.delete": "Delete",
  "article.add": "Add",
  "filter.reset": "Reset",
  "filter.allCategories": "All",
  "search.placeholder": "Search",
  "sort.orderAsc": "In order",
  "sort.titleAsc": "By title",
  "sort.priceDesc": "Expensive at first",
  "sort.editionAsc": "Old ones first",
  "login": "Login",
  "logout": "Logout",
  "submit.login": "Login",
  "login.label": "Username",
  "password.label": "Password",
  "login-form.head": "Login",
  "profile.head": "Profile",
  "profile.name": "Name",
  "profile.phone": "Phone number",
  "profile.email": "email"
}
